[{"City": "Jakarta", "Image": "http://media-cdn.tripadvisor.com/media/photo-s/03/0a/89/5f/normal-gran-melia-jakarta.jpg", "Gym": 0, "MoreThan2pax": 0, "HotelName": "Gran Melia", "Halal": 0, "Under100": 0, "Breakfast": "1", "HotelId": 16}, {"City": "Jakarta", "Image": "http://www.boutiquepicks.com/wp-content/uploads/2013/03/19.jpg", "Gym": 0, "MoreThan2pax": 1, "HotelName": "Morissey Service Apartment", "Halal": 0, "Under100": 0, "Breakfast": 0, "HotelId": 17}, {"City": "Jakarta", "Image": "http://www.hotel.info/media/hotel/pictures/436/436715/HealthClub_635634716855676235.jpg?interpolation=lanczos-none&fit=around%7C545:350&crop=545:350;*,*", "Gym": 1, "MoreThan2pax": 0, "HotelName": "Fairmont Jakarta", "Halal": 0, "Under100": 0, "Breakfast": 0, "HotelId": 18}, {"City": "Jakarta", "Image": "http://luxeinacity.com/wp-content/uploads/2013/The_Keraton_at_The_Plaza_Jakarta_3.jpg", "Gym": 0, "MoreThan2pax": 0, "HotelName": "The Keratin", "Halal": 1, "Under100": 0, "Breakfast": 0, "HotelId": 19}, {"City": "Jakarta", "Image": "http://cdn.ticktab.com/upload/hotels/ID-JK-JKT-000139_Oria-Hotel-Jakarta/hotel_images/original/a8de7c3d9fa43ddbfd714f97d2b276b1.jpg", "Gym": 0, "MoreThan2pax": 0, "HotelName": "ORIA Hotel", "Halal": 0, "Under100": 1, "Breakfast": "1", "HotelId": 20}]